edamampy/__init__.py
edamampy/classes.py
edamampy/cli.py
edamampy/constants.py
edamampy/exceptions.py
edamampy/models.py
edamampy-0.1.dist-info/LICENSE
edamampy-0.1.dist-info/METADATA
edamampy-0.1.dist-info/WHEEL
edamampy-0.1.dist-info/entry_points.txt
edamampy-0.1.dist-info/top_level.txt
edamampy-0.1.dist-info/RECORD
