Metadata-Version: 2.1
Name: edamampy
Version: 0.1
Summary: An easier way of interacting with the edamam recipe search api.
Author: Mark Scharmann
Project-URL: Homepage, https://github.com/ma-a-sc/edamampy
Project-URL: Issues, https://github.com/ma-a-sc/edamampy/issues
Classifier: Programming Language :: Python :: 3
Classifier: License :: OSI Approved :: MIT License
Classifier: Operating System :: OS Independent
Requires-Python: >=3.8
License-File: LICENSE
Requires-Dist: requests
Requires-Dist: pydantic
